model_versioning/version.py
model_versioning/versioning_api.py
util/maven_util.py
aissemble_foundation_versioning_service-2.0.0.dist-info/LICENSE
aissemble_foundation_versioning_service-2.0.0.dist-info/METADATA
aissemble_foundation_versioning_service-2.0.0.dist-info/WHEEL
aissemble_foundation_versioning_service-2.0.0.dist-info/RECORD
