Metadata-Version: 2.3
Name: aissemble-foundation-versioning-service
Version: 2.0.0
Summary: 
License: Apache-2.0
Author: aiSSEMBLE Baseline Community
Author-email: aissemble@bah.com
Requires-Python: >=3.9
Classifier: License :: OSI Approved :: Apache Software License
Classifier: Programming Language :: Python :: 3
Classifier: Programming Language :: Python :: 3.9
Classifier: Programming Language :: Python :: 3.10
Classifier: Programming Language :: Python :: 3.11
Classifier: Programming Language :: Python :: 3.12
Classifier: Programming Language :: Python :: 3.13
Requires-Dist: aissemble-foundation-core-python (==2.0.0)
Requires-Dist: aissemble-foundation-pdp-client-python (==2.0.0)
Requires-Dist: fastapi (>=0.95.0)
Requires-Dist: mlflow (>=2.22.0)
Requires-Dist: urllib3 (>=2.5.0,<3.0.0)
Requires-Dist: uvicorn[standard] (>=0.18.0,<0.19.0)
Project-URL: Documentation, https://boozallen.github.io/aissemble
Project-URL: Homepage, https://github.com/boozallen/aissemble
Project-URL: Repository, https://github.com/boozallen/aissemble
